<?xml version="1.0" encoding="utf-8"?>
<!DOCTYPE urlrewrite
    PUBLIC "-//tuckey.org//DTD UrlRewrite 3.1//EN"
    "http://tuckey.org/res/dtds/urlrewrite3.1.dtd">
<!--
    Configuration file for UrlRewriteFilter
    http://tuckey.org/urlrewrite/
-->
<urlrewrite>

    <rule>
        <from>/css/images/(.*)</from>
        <to type="forward">/css/smoothness/images/$1</to>
    </rule>

    <rule>
        <from>/(currentWeather.)(json|do)</from>
        <to type="redirect">/solarquery/$1$2?%{query-string}</to>
    </rule>

    <rule>
        <from>/(reportableInterval.)(json|do)</from>
        <to type="redirect">/solarquery/$1$2?%{query-string}</to>
    </rule>

    <rule>
        <from>/(.*Data.)(json|do)</from>
        <to type="redirect">/solarquery/$1$2?%{query-string}</to>
    </rule>

</urlrewrite>
